DataAnnotated/__init__.py
DataAnnotated/__main__.py
DataAnnotated/main.py
DataAnnotated/Utils/__init__.py
DataAnnotated/Utils/api.py
DataAnnotated/Utils/decorators.py
DataAnnotated/Utils/utils.py
DataAnnotated/constants/__init__.py
DataAnnotated/constants/path.py
DataAnnotated/src/__init__.py
DataAnnotated/src/core.py
DataAnnotated/src/text.py
DataAnnotated-1.0.0.dist-info/LICENSE
DataAnnotated-1.0.0.dist-info/METADATA
DataAnnotated-1.0.0.dist-info/WHEEL
DataAnnotated-1.0.0.dist-info/top_level.txt
DataAnnotated-1.0.0.dist-info/RECORD
