Metadata-Version: 2.1
Name: DataAnnotated
Version: 1.0.0
Summary: Python package for DataAnnotated platform
Home-page: https://github.com/SiddeshSambasivam/DataAnnotated-PythonPackage
Author: Siddesh Sambasivam Suseela
Author-email: plutocrat45@gmail.com
License: UNKNOWN
Project-URL: Bug Tracker, https://github.com/SiddeshSambasivam/DataAnnotated-PythonPackage/issues
Platform: UNKNOWN
Classifier: Programming Language :: Python :: 3
Classifier: License :: OSI Approved :: MIT License
Classifier: Operating System :: OS Independent
Requires-Python: >=3.7.9
Requires-Dist: appdirs (==1.4.4)
Requires-Dist: args (==0.1.0)
Requires-Dist: certifi (==2020.12.5)
Requires-Dist: chardet (==4.0.0)
Requires-Dist: click (==7.1.2)
Requires-Dist: clint (==0.5.1)
Requires-Dist: colorama (==0.4.4)
Requires-Dist: idna (==2.10)
Requires-Dist: numpy (==1.20.1)
Requires-Dist: pandas (==1.2.2)
Requires-Dist: prompt-toolkit (==1.0.14)
Requires-Dist: pyfiglet (==0.7)
Requires-Dist: Pygments (==2.8.0)
Requires-Dist: PyInquirer (==1.0.3)
Requires-Dist: python-dateutil (==2.8.1)
Requires-Dist: pytz (==2021.1)
Requires-Dist: regex (==2020.11.13)
Requires-Dist: requests (==2.25.1)
Requires-Dist: six (==1.15.0)
Requires-Dist: termcolor (==1.1.0)
Requires-Dist: urllib3 (==1.26.3)
Requires-Dist: wcwidth (==0.2.5)
